runez/__init__.py
runez/__main__.py
runez/_inspect.py
runez/ascii.py
runez/click.py
runez/config.py
runez/conftest.py
runez/convert.py
runez/date.py
runez/file.py
runez/heartbeat.py
runez/http.py
runez/inspector.py
runez/logsetup.py
runez/program.py
runez/prompt.py
runez/py.typed
runez/pyenv.py
runez/render.py
runez/schema.py
runez/serialize.py
runez/system.py
runez/thread.py
runez/colors/__init__.py
runez/colors/named.py
runez/colors/terminal.py
runez-5.4.1.dist-info/licenses/LICENSE
runez-5.4.1.dist-info/METADATA
runez-5.4.1.dist-info/WHEEL
runez-5.4.1.dist-info/top_level.txt
runez-5.4.1.dist-info/RECORD
